{"base.md":"DeUlSxC4","index.md":"B90yPDGl","ssu_base_faq.md":"CYKQR-Yf","ssu_base_feats.md":"N7KicJ-2","ssu_base_install.md":"ChP8C9pK","ssu_base_overview.md":"DCvWciaY","ssu_dev_module_builder.md":"DiECCI6Q","ssu_dev_module_cfgui.md":"7bnOprz4","ssu_dev_module_index.md":"DPJZxxf5","ssu_dev_module_kernel.md":"XU3Bt1c8","ssu_dev_module_manager.md":"C_fIbpNC","ssu_dev_module_root.md":"CQuaJtHh","ssu_dev_module_webui.md":"BFYjXMSd","ssu_dev_scheme.md":"4VQAP1t5","ssu_more_license.md":"DVu5FzTC","ssu_more_privacy.md":"D6hQJsf0","ssu_more_translation.md":"Bg4uQ4KY","ssu_ssu_3q.md":"B3ia66BH","ssu_ssu_compat.md":"DqpK3CRS","ssu_ssu_defense.md":"CMk5h-F9","ssu_ssu_origin.md":"XEmuYOAG","ssu_ssu_principle.md":"BTL0Gujj","ssu_update_changelog.md":"DFKVio8U","ssu_update_history.md":"PTT0t9vs","suu_appendix_android_mode.md":"7XS3XLrE","suu_appendix_android_path.md":"VtaKi2J3","suu_appendix_android_tip.md":"DVQVCmkt","suu_changelog_android.md":"CelRg4EV","suu_changelog_windows.md":"BCETKHOb","suu_feat_android_c_c.md":"CXbuyUNX","suu_feat_android_gbb.md":"BaDXqkkf","suu_feat_android_modify.my.id.md":"DNhbQz6g","suu_feat_android_nyanya.md":"-fQstmPW","suu_feat_android_toybox.md":"DXLXz21_","suu_feat_android_xposed.md":"ChArb9ur","suu_know.md":"D_AYTdI0","suu_more_agreement.md":"BZdcjJjl","suu_more_license.md":"4rb9C0pZ","suu_more_privacy.md":"BQDt_ed3","suu_start_android.md":"CrMDwWxK","suu_start_windows.md":"BI6-g2C3"}
